cognite/turbulent_flux/__init__.py
cognite/turbulent_flux/client.py
cognite/turbulent_flux/config.py
cognite/turbulent_flux/utils.py
cognite_turbulent_flux_sdk-0.0.3.dist-info/LICENSE
cognite_turbulent_flux_sdk-0.0.3.dist-info/METADATA
cognite_turbulent_flux_sdk-0.0.3.dist-info/WHEEL
cognite_turbulent_flux_sdk-0.0.3.dist-info/top_level.txt
cognite_turbulent_flux_sdk-0.0.3.dist-info/RECORD
