Metadata-Version: 2.1
Name: cognite-turbulent-flux-sdk
Version: 0.0.3
Summary: UNKNOWN
Home-page: UNKNOWN
License: UNKNOWN
Platform: UNKNOWN
Requires-Python: >=3.7
Requires-Dist: pandas
Requires-Dist: numpy
Requires-Dist: scipy
Requires-Dist: requests
